Workbook

Sheet Ventas
A1: Comercial Norte S.A. — Registro de Ventas 2024
A2: # | B2: Fecha | C2: Producto | D2: Categoría | E2: Cantidad | F2: Precio Unit. ($) | H2: Vendedor | I2: Región
A3: 1 | B3: 2024-01-12 | C3: Escritorio | D3: Mobiliario | E3: 9 | F3: 350 | G3: =E3*F3 -> 3150 | H3: Carlos Ríos | I3: Sur
A4: 2 | B4: 2024-11-25 | C4: Escritorio | D4: Mobiliario | E4: 18 | F4: 180 | G4: =E4*F4 -> 3240 | H4: Sofía Ruiz | I4: Oriente
A5: 3 | B5: 2024-01-12 | C5: Silla de oficina | D5: Mobiliario | E5: 3 | F5: 350 | G5: =E5*F5 -> 1050 | H5: Carlos Ríos | I5: Norte
A6: 4 | B6: 2024-01-12 | C6: Mouse óptico | D6: Tecnología | E6: 18 | F6: 380 | G6: =E6*F6 -> 6840 | H6: Sofía Ruiz | I6: Oriente
A7: 5 | B7: 2024-08-05 | C7: Monitor 24" | D7: Tecnología | E7: 19 | F7: 520 | G7: =E7*F7 -> 9880 | H7: Ana Gómez | I7: Sur
A8: 6 | B8: 2024-06-12 | C8: Carpetas AZ | D8: Papelería | E8: 9 | F8: 15 | G8: =E8*F8 -> 135 | H8: Carlos Ríos | I8: Centro
A9: 7 | B9: 2024-02-12 | C9: Escritorio | D9: Mobiliario | E9: 13 | F9: 180 | G9: =E9*F9 -> 2340 | H9: Lucía Pardo | I9: Centro
A10: 8 | B10: 2024-05-05 | C10: Mouse óptico | D10: Tecnología | E10: 2 | F10: 95 | G10: =E10*F10 -> 190 | H10: Sofía Ruiz | I10: Norte
A11: 9 | B11: 2024-02-12 | C11: Carpetas AZ | D11: Papelería | E11: 18 | F11: 22 | G11: =E11*F11 -> 396 | H11: Sofía Ruiz | I11: Centro
A12: 10 | B12: 2024-04-05 | C12: Mouse óptico | D12: Tecnología | E12: 3 | F12: 250 | G12: =E12*F12 -> 750 | H12: Carlos Ríos | I12: Centro
A13: 11 | B13: 2024-04-18 | C13: Escritorio | D13: Mobiliario | E13: 4 | F13: 290 | G13: =E13*F13 -> 1160 | H13: Lucía Pardo | I13: Oriente
A14: 12 | B14: 2024-03-18 | C14: Resma de papel | D14: Papelería | E14: 12 | F14: 22 | G14: =E14*F14 -> 264 | H14: Carlos Ríos | I14: Sur
... A82: 80 | B82: 2024-01-05 | C82: Carpetas AZ | D82: Papelería | E82: 17 | F82: 15 | G82: =E82*F82 -> 255 | H82: Lucía Pardo | I82: Oriente
A83: TOTAL | G83: =SUM(G3:G82) -> 122289

Sheet Gastos
A1: Comercial Norte S.A. — Control de Gastos 2024
A2: # | B2: Mes | C2: Categoría | D2: Descripción | E2: Proveedor | F2: Monto ($) | G2: Estado
A3: 1 | B3: Enero | C3: Nómina | D3: Gasto nómina Enero | E3: Claro Empresa | F3: 3734 | G3: Pagado
A4: 2 | B4: Enero | C4: Arriendo | D4: Gasto arriendo Enero | E4: Papelería Central | F4: 4889 | G4: Pagado
A5: 3 | B5: Enero | C5: Nómina | D5: Gasto nómina Enero | E5: TransLogística | F5: 975 | G5: Pagado
A6: 4 | B6: Enero | C6: Arriendo | D6: Gasto arriendo Enero | E6: Inmobiliaria Sur | F6: 4052 | G6: Pendiente
A7: 5 | B7: Febrero | C7: Arriendo | D7: Gasto arriendo Febrero | E7: Claro Empresa | F7: 1243 | G7: Pendiente
A8: 6 | B8: Febrero | C8: Arriendo | D8: Gasto arriendo Febrero | E8: Papelería Central | F8: 5132 | G8: Pagado
A9: 7 | B9: Febrero | C9: Servicios | D9: Gasto servicios Febrero | E9: Softtech | F9: 5639 | G9: Pagado
A10: 8 | B10: Febrero | C10: Logística | D10: Gasto logística Febrero | E10: TransLogística | F10: 3749 | G10: Pagado
A11: 9 | B11: Marzo | C11: Servicios | D11: Gasto servicios Marzo | E11: Inmobiliaria Sur | F11: 5060 | G11: Pagado
A12: 10 | B12: Marzo | C12: Nómina | D12: Gasto nómina Marzo | E12: Agencia Pixel | F12: 1681 | G12: Pagado
A13: 11 | B13: Marzo | C13: Logística | D13: Gasto logística Marzo | E13: Banco Nómina | F13: 5089 | G13: Pagado
A14: 12 | B14: Marzo | C14: Arriendo | D14: Gasto arriendo Marzo | E14: TransLogística | F14: 5179 | G14: Pagado
... A50: 48 | B50: Diciembre | C50: Servicios | D50: Gasto servicios Diciembre | E50: Inmobiliaria Sur | F50: 2210 | G50: Pendiente
A51: TOTAL | F51: =SUM(F3:F50) -> 179765

Sheet Empleados
A1: Comercial Norte S.A. — Lista de Empleados
A2: ID | B2: Nombre completo | C2: Área | D2: Cargo | E2: Fecha ingreso | F2: Salario ($) | G2: Estado | H2: Años en empresa
A3: E001 | B3: Ana Gómez | C3: Ventas | D3: Ejecutiva de ventas | E3: 2019-03-15 | F3: 2800 | G3: Activo | H3: =IF(E3<>"",DATEDIF(E3,TODAY(),"Y")&" años","") -> 7 años
A4: E002 | B4: Carlos Ríos | C4: Ventas | D4: Ejecutivo de ventas | E4: 2021-07-01 | F4: 2500 | G4: Activo | H4: =IF(E4<>"",DATEDIF(E4,TODAY(),"Y")&" años","") -> 4 años
A5: E003 | B5: Lucía Pardo | C5: Ventas | D5: Senior de ventas | E5: 2017-11-20 | F5: 3200 | G5: Activo | H5: =IF(E5<>"",DATEDIF(E5,TODAY(),"Y")&" años","") -> 8 años
A6: E004 | B6: Martín Vera | C6: Ventas | D6: Ejecutivo de ventas | E6: 2022-01-10 | F6: 2400 | G6: Activo | H6: =IF(E6<>"",DATEDIF(E6,TODAY(),"Y")&" años","") -> 4 años
A7: E005 | B7: Sofía Ruiz | C7: Ventas | D7: Jefa de ventas | E7: 2015-06-05 | F7: 4500 | G7: Activo | H7: =IF(E7<>"",DATEDIF(E7,TODAY(),"Y")&" años","") -> 10 años
A8: E006 | B8: Roberto León | C8: Contabilidad | D8: Contador | E8: 2018-09-12 | F8: 3100 | G8: Activo | H8: =IF(E8<>"",DATEDIF(E8,TODAY(),"Y")&" años","") -> 7 años
A9: E007 | B9: Paola Salas | C9: Contabilidad | D9: Auxiliar contable | E9: 2023-02-28 | F9: 1900 | G9: Activo | H9: =IF(E9<>"",DATEDIF(E9,TODAY(),"Y")&" años","") -> 3 años
A10: E008 | B10: Diego Mora | C10: Logística | D10: Coordinador logístico | E10: 2016-04-18 | F10: 3400 | G10: Activo | H10: =IF(E10<>"",DATEDIF(E10,TODAY(),"Y")&" años","") -> 10 años
A11: E009 | B11: Valeria Cruz | C11: Logística | D11: Asistente logística | E11: 2023-08-01 | F11: 2000 | G11: Activo | H11: =IF(E11<>"",DATEDIF(E11,TODAY(),"Y")&" años","") -> 2 años
A12: E010 | B12: Fernando Díaz | C12: Tecnología | D12: Analista TI | E12: 2020-05-22 | F12: 3600 | G12: Activo | H12: =IF(E12<>"",DATEDIF(E12,TODAY(),"Y")&" años","") -> 5 años
A13: E011 | B13: Isabel Torres | C13: Marketing | D13: Diseñadora gráfica | E13: 2021-11-15 | F13: 2700 | G13: Activo | H13: =IF(E13<>"",DATEDIF(E13,TODAY(),"Y")&" años","") -> 4 años
A14: E012 | B14: Andrés Campos | C14: Gerencia | D14: Gerente general | E14: 2012-01-03 | F14: 7500 | G14: Activo | H14: =IF(E14<>"",DATEDIF(E14,TODAY(),"Y")&" años","") -> 14 años
... A17: E015 | B17: Gloria Reyes | C17: Contabilidad | D17: Gerente financiera | E17: 2013-05-14 | F17: 5800 | G17: Activo | H17: =IF(E17<>"",DATEDIF(E17,TODAY(),"Y")&" años","") -> 12 años

Sheet Resumen
A1: Comercial Norte S.A. — Dashboard Resumen 2024
A3: RESUMEN DE VENTAS
A4: Total ventas 2024 ($) | B4: =SUM(Ventas!G3:G82) -> 122289
A5: Número de transacciones | B5: =COUNTA(Ventas!A3:A82) -> 80
A6: Promedio por venta ($) | B6: =AVERAGE(Ventas!G3:G82) -> 1528.6125
A7: Venta máxima ($) | B7: =MAX(Ventas!G3:G82) -> 9880
A8: Venta mínima ($) | B8: =MIN(Ventas!G3:G82) -> 8
A10: RESUMEN DE GASTOS
A11: Total gastos 2024 ($) | B11: =SUM(Gastos!F3:F50) -> 179765
A12: Gastos pendientes ($) | B12: =SUMIF(Gastos!G3:G50,"Pendiente",Gastos!F3:F50) -> 46145
A13: Gastos pagados ($) | B13: =SUMIF(Gastos!G3:G50,"Pagado",Gastos!F3:F50) -> 133620
A14: Margen neto ($) | B14: =B4-B11 -> -57476
A16: RESUMEN DE EMPLEADOS
A17: Total empleados | B17: =COUNTA(Empleados!A3:A17) -> 15 | E17: Ana Gómez | F17: =SUMIF(Ventas!H3:H82,E17,Ventas!G3:G82) -> 37279
A18: Empleados activos | B18: =COUNTIF(Empleados!G3:G17,"Activo") -> 14 | E18: Carlos Ríos | F18: =SUMIF(Ventas!H3:H82,E18,Ventas!G3:G82) -> 24546
A19: Salario promedio ($) | B19: =AVERAGE(Empleados!F3:F17) -> 3480 | E19: Lucía Pardo | F19: =SUMIF(Ventas!H3:H82,E19,Ventas!G3:G82) -> 19211
A20: Nómina mensual total ($) | B20: =SUMIF(Empleados!G3:G17,"Activo",Empleados!F3:F17) -> 49600 | E20: Martín Vera | F20: =SUMIF(Ventas!H3:H82,E20,Ventas!G3:G82) -> 4926
E21: Sofía Ruiz | F21: =SUMIF(Ventas!H3:H82,E21,Ventas!G3:G82) -> 36327
A22: NOTA DEL CURSO: Este dashboard se construye progresivamente con Claude a lo largo del curso. Al finalizar el Módulo 3 tendrás este resumen completo funcionando.

Sheet Errores_Demo
A1: Comercial Norte S.A. — Reporte de Comisiones y Precios 2024
A2: Producto | B2: Cantidad | C2: Precio ($) | D2: Total ($) | E2: Descuento (%)
A3: Laptop | B3: 5 | C3: 850 | D3: =B3*C3 -> 4250 | E3: 0.1
A4: Monitor | B4: 3 | C4: 320 | D4: =B4*C99 -> 0
A5: Teclado | B5: 10 | C5: 45 | D5: =B5*C5 -> 450 | E5: 0.1
A6: Mouse | B6: 8 | D6: =B6*A6 -> #VALUE!
A7: Silla oficina | B7: 2 | C7: 380 | D7: =B7*C7 -> 760 | E7: 0.1
A8: Precio promedio | C8: =SUM(C3:C7)/0 -> #DIV/0! | D8: =SUM(D3:D7) -> #VALUE!
A10: Cálculo de Bonos por Vendedor — Tecnología Q4 2024
A11: Vendedor | B11: Categoría | C11: Condición | D11: % Bono | E11: Bono calculado ($)
A12: Ana Gómez | B12: Tecnología | C12: >Promedio general | D12: 10% / 5% | E12: =IF(SUMIFS([1]Ventas!G:G,[1]Ventas!H:H,"Ana Gómez",[1]Ventas!D:D,"Tecnología")>AVERAGE([1]Ventas!G:G),SUM([1]Ventas!G:G)*10%,SUM([1]Ventas!G:G)*5%) -> #VALUE!

Sheet Formulas_Avanzadas
A1: Comercial Norte S.A. — Fórmulas Avanzadas (Demo clase 2.3)
A2: Fórmulas reales que parecen complicadas — Claude las explica en lenguaje simple
A4: Nombre | B4: ¿Qué hace? | C4: Fórmula real | D4: Usada en | E4: Explicación simple
A5: BUSCARV anidado | B5: Buscar el salario de un vendedor por su nombre | C5: '=IFERROR(VLOOKUP(A6,Empleados!B:F,5,0),"No encontrado") | D5: Clase 2.3 · Módulo 2 | E5: Busca 'Ana Gómez' en la hoja Empleados y trae su salario. Si no existe, muestra 'No encontrado'.
A6: SUMAR.SI.CONJUNTO | B6: Total ventas de Ana Gómez en la región Norte | C6: '=SUMIFS(Ventas!G:G,Ventas!H:H,"Ana Gómez",Ventas!I:I,"Norte") | D6: Clase 2.3 · Módulo 2 | E6: Suma solo las ventas donde el vendedor ES Ana Gómez Y la región ES Norte al mismo tiempo.
A7: SI con múltiples condiciones | B7: Clasificar venta como Alta, Media o Baja | C7: '=IF(Ventas!G3>=5000,"Alta",IF(Ventas!G3>=1000,"Media","Baja")) | D7: Clase 2.3 · Módulo 2 | E7: Si el total es 5000 o más → Alta. Si es entre 1000 y 4999 → Media. Si es menos de 1000 → Baja.
A8: CONTAR.SI.CONJUNTO | B8: Cuántas ventas de Tecnología superan $500 | C8: '=COUNTIFS(Ventas!D:D,"Tecnología",Ventas!G:G,">=500") | D8: Clase 2.3 · Módulo 2 | E8: Cuenta las filas donde la categoría ES Tecnología Y el total es mayor o igual a 500.
A9: TEXTO + CONCATENAR | B9: Crear etiqueta legible de fecha de ingreso | C9: '=TEXT(Empleados!E3,"DD/MM/YYYY")&" — "&Empleados!D3 | D9: Clase 2.3 · Módulo 2 | E9: Une la fecha de ingreso formateada con el cargo del empleado para crear una etiqueta completa.
A10: ÍNDICE + COINCIDIR | B10: Buscar empleado por salario máximo | C10: '=INDEX(Empleados!B3:B17,MATCH(MAX(Empleados!F3:F17),Empleados!F3:F17,0)) | D10: Módulo avanzado (Udemy) | E10: Encuentra el nombre del empleado con el salario más alto. Más flexible que BUSCARV.
A11: PROMEDIO.SI | B11: Promedio de ventas solo de la región Sur | C11: '=AVERAGEIF(Ventas!I:I,"Sur",Ventas!G:G) | D11: Clase 2.3 · Módulo 2 | E11: Calcula el promedio de la columna Total, pero solo para las filas donde la región es Sur.

Sheet Datos sucios
A1: Comercial Norte S.A. — Base de Proveedores (datos importados)
A2: # | B2: Proveedor | C2: Categoría | D2: Fecha factura | E2: Monto ($) | F2: Estado pago
A3: 1 | B3: TransLogística | C3: Logística | D3: 15/03/2024 | E3: 1250 | F3: Pagado
A4: 2 | B4: Inmobiliaria Sur | C4: ARRIENDO | D4: 2024-04-01 | E4: 4500 | F4: PAGADO
A5: 3 | B5: Claro Empresa | C5: Servicios | D5: 1 Ene 2024 | E5: 890 | F5: pagado
A6: 4 | B6: AGENCIA PIXEL | C6: marketing | D6: 22/01/2024 | E6: 2100 | F6: Pendiente
A7: 5 | B7: Softtech | C7: Tecnología | D7: 2024-02-14 | E7: $3,400.00 | F7: Pago
A8: 6
A9: 7 | B9: Banco Nómina | C9: Nómina | D9: 05/05/2024 | E9: 7200 | F9: pagado
A10: 8 | B10: papelería central | C10: Papelería | D10: 15-06-2024 | E10: 320 | F10: Si
A11: 9 | B11: TransLogistica | C11: logística | D11: 2024-07-18 | E11: 1800 | F11: PENDIENTE
A12: 10 | B12: Inmobiliaria sur | C12: Arriendo | D12: 30/07/2024 | E12: 4500 | F12: Pagado
A13: 11 | B13: Claro Empresa | C13: SERVICIOS | D13: Aug 12 2024 | E13: 890 | F13: Pagado
A14: 12
A15: 13 | B15: Agencia Pixel | C15: Marketing | D15: 2024-09-05 | E15: 2.100,00 | F15: pendiente
A16: 14 | B16: SOFTTECH | C16: Tecnología | D16: 10/10/2024 | E16: 3400 | F16: PAGADO
A17: 15 | B17: Banco Nomina | C17: nómina | D17: 2024-11-01 | E17: 7200 | F17: Pagado
A18: 16 | B18: TransLogística | C18: Logística | D18: 15/11/2024 | E18: 1,800 USD | F18: Pagado
A19: 17 | B19: Papelería Central | C19: papelería | D19: 01-12-2024 | E19: 320 | F19: No pagado
A20: 18 | B20: Inmobiliaria Sur | C20: arriendo | D20: 2024-12-15 | E20: 4500 | F20: pendiente
A21: 19 | B21: claro empresa | C21: Servicios | D21: 28/12/2024 | E21: 890 | F21: PAGADO
A22: 20 | B22: Agencia Pixel | C22: Marketing | D22: 31/12/2024 | E22: 2100 | F22: Pagado

Sheet Datos limpios
A1: Comercial Norte S.A. — Base de Proveedores (limpia)
A2: # | B2: Proveedor | C2: Categoría | D2: Fecha Factura | E2: Monto ($) | F2: Estado Pago
A3: 1 | B3: TransLogística | C3: Logística | D3: 45366 | E3: 1250 | F3: Pagado
A4: 2 | B4: Inmobiliaria Sur | C4: Arriendo | D4: 45383 | E4: 4500 | F4: Pagado
A5: 3 | B5: Claro Empresa | C5: Servicios | D5: 45292 | E5: 890 | F5: Pagado
A6: 4 | B6: Agencia Pixel | C6: Marketing | D6: 45313 | E6: 2100 | F6: Pendiente
A7: 5 | B7: Softtech | C7: Tecnología | D7: 45336 | E7: 3400 | F7: Pagado
A8: 6 | B8: Banco Nómina | C8: Nómina | D8: 45417 | E8: 7200 | F8: Pagado
A9: 7 | B9: Papelería Central | C9: Papelería | D9: 45458 | E9: 320 | F9: Pagado
A10: 8 | B10: TransLogística | C10: Logística | D10: 45491 | E10: 1800 | F10: Pendiente
A11: 9 | B11: Inmobiliaria Sur | C11: Arriendo | D11: 45503 | E11: 4500 | F11: Pagado
A12: 10 | B12: Claro Empresa | C12: Servicios | D12: 45516 | E12: 890 | F12: Pagado
A13: 11 | B13: Agencia Pixel | C13: Marketing | D13: 45540 | E13: 2100 | F13: Pendiente
A14: 12 | B14: Softtech | C14: Tecnología | D14: 45575 | E14: 3400 | F14: Pagado
... A20: 18 | B20: Agencia Pixel | C20: Marketing | D20: 45657 | E20: 2100 | F20: Pagado
